prefect_extensions/__init__.py
prefect_extensions/portal.py
prefect_extensions-0.1.0.dist-info/WHEEL
prefect_extensions-0.1.0.dist-info/METADATA
prefect_extensions-0.1.0.dist-info/RECORD
