Metadata-Version: 2.1
Name: prefect-extensions
Version: 0.1.0
Summary: 
Author: Daniel Neururer
Author-email: neud@zhaw.ch
Requires-Python: >=3.9,<4.0
Classifier: Programming Language :: Python :: 3
Classifier: Programming Language :: Python :: 3.10
Classifier: Programming Language :: Python :: 3.9
Requires-Dist: prefect (>=2.0b,<3.0)
Requires-Dist: pydantic (>=1.9.1,<2.0.0)
